langma/__init__.py
langma/__version__.py
langma/cli.py
langma/corpus.py
langma/generators.py
langma/macros.py
langma/types.py
langma/callbacks/__init__.py
langma/callbacks/eval_callBack.py
langma/callbacks/save_callback.py
langma/embeddings/__init__.py
langma/embeddings/abc_embedding.py
langma/embeddings/bare_embedding.py
langma/embeddings/bert_embedding.py
langma/embeddings/transformer_embedding.py
langma/embeddings/word_embedding.py
langma/layers/__init__.py
langma/layers/behdanau_attention.py
langma/layers/conditional_random_field.py
langma/metrics/__init__.py
langma/metrics/multi_label_classification.py
langma/metrics/sequence_labeling.py
langma/processors/__init__.py
langma/processors/abc_processor.py
langma/processors/class_processor.py
langma/processors/sequence_processor.py
langma/processors/tools.py
langma/tasks/__init__.py
langma/tasks/abs_task_model.py
langma/tasks/classification/__init__.py
langma/tasks/classification/abc_model.py
langma/tasks/classification/bi_gru_model.py
langma/tasks/classification/bi_lstm_model.py
langma/tasks/classification/cnn_attention_model.py
langma/tasks/classification/cnn_gru_model.py
langma/tasks/classification/cnn_lstm_model.py
langma/tasks/classification/cnn_model.py
langma/tasks/labeling/__init__.py
langma/tasks/labeling/abc_model.py
langma/tasks/labeling/bi_gru_crf_model.py
langma/tasks/labeling/bi_gru_model.py
langma/tasks/labeling/bi_lstm_crf_model.py
langma/tasks/labeling/bi_lstm_model.py
langma/tasks/labeling/cnn_lstm_model.py
langma/tasks/seq2seq/__init__.py
langma/tasks/seq2seq/model.py
langma/tasks/seq2seq/decoder/__init__.py
langma/tasks/seq2seq/decoder/att_gru_decoder.py
langma/tasks/seq2seq/decoder/gru_decoder.py
langma/tasks/seq2seq/encoder/__init__.py
langma/tasks/seq2seq/encoder/gru_encoder.py
langma/tokenizers/__init__.py
langma/tokenizers/base_tokenizer.py
langma/tokenizers/bert_tokenizer.py
langma/tokenizers/jieba_tokenizer.py
langma/utils/__init__.py
langma/utils/_types.py
langma/utils/clean_data.py
langma-0.0.8.dist-info/LICENSE
langma-0.0.8.dist-info/METADATA
langma-0.0.8.dist-info/WHEEL
langma-0.0.8.dist-info/entry_points.txt
langma-0.0.8.dist-info/top_level.txt
langma-0.0.8.dist-info/RECORD
