Metadata-Version: 2.1
Name: langma
Version: 0.0.8
Summary: Awesome NLP framework you are waiting for ✨
Home-page: https://github.com/szj2ys/langma
Author: SZJ
Author-email: szj2ys@qq.com
License: MIT
Platform: UNKNOWN
Classifier: Development Status :: 1 - Planning
Classifier: License :: OSI Approved :: MIT License
Classifier: Programming Language :: Python :: 3
Requires-Python: >=3.5.0
License-File: LICENSE
Requires-Dist: numpy (>=1.18.1)
Requires-Dist: pandas (>=1.0.1)
Requires-Dist: tqdm
Requires-Dist: jieba
Requires-Dist: matplotlib
Requires-Dist: plotly (~=5.6.0)
Requires-Dist: wordcloud (~=1.8.1)
Requires-Dist: bert4keras (>=0.9.1)
Requires-Dist: scikit-learn (>=0.24.0)
Requires-Dist: keras (>=2.2.4)
Requires-Dist: tensorflow (>=2.0.0)
Requires-Dist: tensorflow-addons
Requires-Dist: click
Requires-Dist: click-help-colors
